rail_lib_gp_comp/__init__.py
rail_lib_gp_comp/_version.py
rail_lib_gp_comp-0.0.1.dist-info/LICENSE
rail_lib_gp_comp-0.0.1.dist-info/METADATA
rail_lib_gp_comp-0.0.1.dist-info/WHEEL
rail_lib_gp_comp-0.0.1.dist-info/top_level.txt
rail_lib_gp_comp-0.0.1.dist-info/RECORD
